odoo/addons/agreement_rebate/README.rst
odoo/addons/agreement_rebate/__init__.py
odoo/addons/agreement_rebate/__manifest__.py
odoo/addons/agreement_rebate/data/agreement_rebate_data.xml
odoo/addons/agreement_rebate/i18n/agreement_rebate.pot
odoo/addons/agreement_rebate/i18n/es.po
odoo/addons/agreement_rebate/migrations/13.0.1.0.0/post-migration.py
odoo/addons/agreement_rebate/migrations/13.0.1.0.0/pre-migration.py
odoo/addons/agreement_rebate/models/__init__.py
odoo/addons/agreement_rebate/models/account_invoice.py
odoo/addons/agreement_rebate/models/agreement.py
odoo/addons/agreement_rebate/models/agreement_rebate_settlement.py
odoo/addons/agreement_rebate/models/agreement_type.py
odoo/addons/agreement_rebate/readme/CONTRIBUTORS.rst
odoo/addons/agreement_rebate/readme/DESCRIPTION.rst
odoo/addons/agreement_rebate/readme/USAGE.rst
odoo/addons/agreement_rebate/security/agreement_rebate_security.xml
odoo/addons/agreement_rebate/security/ir.model.access.csv
odoo/addons/agreement_rebate/static/description/icon.png
odoo/addons/agreement_rebate/static/description/index.html
odoo/addons/agreement_rebate/static/img/agreement_discount_global.png
odoo/addons/agreement_rebate/static/img/agreement_discount_line.png
odoo/addons/agreement_rebate/static/img/agreement_discount_section.png
odoo/addons/agreement_rebate/static/img/agreement_discount_section_rule_match.png
odoo/addons/agreement_rebate/static/img/agreement_rebate_lines_filter.png
odoo/addons/agreement_rebate/static/img/create_settlement_invoices.png
odoo/addons/agreement_rebate/static/img/create_settlements_wizard.png
odoo/addons/agreement_rebate/tests/__init__.py
odoo/addons/agreement_rebate/tests/test_agreement_rebate.py
odoo/addons/agreement_rebate/views/agreement_condition_view.xml
odoo/addons/agreement_rebate/views/agreement_menu_view.xml
odoo/addons/agreement_rebate/views/agreement_rebate_settlement_view.xml
odoo/addons/agreement_rebate/views/agreement_type.xml
odoo/addons/agreement_rebate/views/agreement_view.xml
odoo13_addon_agreement_rebate-13.0.1.0.1.dist-info/METADATA
odoo13_addon_agreement_rebate-13.0.1.0.1.dist-info/WHEEL
odoo13_addon_agreement_rebate-13.0.1.0.1.dist-info/top_level.txt
odoo13_addon_agreement_rebate-13.0.1.0.1.dist-info/RECORD
